rtl/interlock_controller.sv
`default_nettype none

module interlock_controller #(
    parameter [7:0] WARNING_THRESHOLD = 8'd20,
    parameter [7:0] DANGER_THRESHOLD  = 8'd50
) (
    input  logic       clk,
    input  logic       reset,
    input  logic [7:0] vibration_level,
    input  logic       transient_event,
    output logic [1:0] state,
    output logic       warning,
    output logic       interlock,
    output logic       motor_enable,
    output logic       event_latched
);
    // Keep these untyped for compatibility with the older Yosys release
    // installed on the ECE270 lab machines.
    localparam [1:0] NORMAL = 2'd0;
    localparam [1:0] WARN   = 2'd1;
    localparam [1:0] TRIP   = 2'd2;

    always_ff @(posedge clk or posedge reset) begin
        if (reset) begin
            state         <= NORMAL;
            event_latched <= 1'b0;
        end else begin
            if (transient_event)
                event_latched <= 1'b1;

            if (state == TRIP || transient_event ||
                vibration_level >= DANGER_THRESHOLD)
                state <= TRIP;
            else if (vibration_level >= WARNING_THRESHOLD)
                state <= WARN;
            else
                state <= NORMAL;
        end
    end

    always_comb begin
        warning      = (state == WARN);
        interlock    = (state == TRIP);
        motor_enable = (state != TRIP);
    end
endmodule

`default_nettype wire

tb/interlock_controller_tb.sv
`timescale 1ns/1ps
`default_nettype none

module interlock_controller_tb;
    logic clk = 0;
    logic reset = 0;
    logic [7:0] vibration_level = 0;
    logic transient_event = 0;
    logic [1:0] state;
    logic warning, interlock, motor_enable, event_latched;

    always #5 clk = ~clk;

    interlock_controller dut (.*);

    task automatic check(input logic [1:0] expected_state,
                         input logic expected_motor,
                         input string label);
        @(negedge clk);
        if (state !== expected_state || motor_enable !== expected_motor) begin
            $error("%s: state=%0d motor=%0b", label, state, motor_enable);
            $fatal(1);
        end
    endtask

    initial begin
        $dumpfile("build/interlock_controller.vcd");
        $dumpvars(0, interlock_controller_tb);

        reset = 1; repeat (2) @(posedge clk); @(negedge clk); reset = 0;
        vibration_level = 8'd5;  check(2'd0, 1'b1, "NORMAL");
        vibration_level = 8'd30; check(2'd1, 1'b1, "WARNING");
        vibration_level = 8'd70; check(2'd2, 1'b0, "VIBRATION TRIP");

        vibration_level = 8'd5;  check(2'd2, 1'b0, "TRIP LATCHED");
        reset = 1; @(posedge clk); @(negedge clk); reset = 0;
        check(2'd0, 1'b1, "RESET");

        // Change synchronous inputs away from the active clock edge. This
        // avoids a testbench/DUT scheduling race on older Icarus versions.
        @(negedge clk);
        transient_event = 1;
        @(negedge clk);
        transient_event = 0;
        check(2'd2, 1'b0, "ESD_SIM TRIP");
        if (!event_latched) $fatal(1, "event_latched was not set");

        $display("PASS: interlock_controller_tb");
        $finish;
    end
endmodule

`default_nettype wire

build/interlock_controller.vcd
$date
	Thu Jul 30 15:23:15 2026
$end
$version
	Icarus Verilog
$end
$timescale
	1ps
$end
$scope module interlock_controller_tb $end
$var wire 1 ! warning $end
$var wire 2 " state [1:0] $end
$var wire 1 # motor_enable $end
$var wire 1 $ interlock $end
$var wire 1 % event_latched $end
$var reg 1 & clk $end
$var reg 1 ' reset $end
$var reg 1 ( transient_event $end
$var reg 8 ) vibration_level [7:0] $end
$scope module dut $end
$var wire 1 & clk $end
$var wire 1 ' reset $end
$var wire 1 ( transient_event $end
$var wire 8 * vibration_level [7:0] $end
$var parameter 8 + DANGER_THRESHOLD $end
$var parameter 2 , NORMAL $end
$var parameter 2 - TRIP $end
$var parameter 2 . WARN $end
$var parameter 8 / WARNING_THRESHOLD $end
$var reg 1 % event_latched $end
$var reg 1 $ interlock $end
$var reg 1 # motor_enable $end
$var reg 2 0 state [1:0] $end
$var reg 1 ! warning $end
$upscope $end
$scope task check $end
$upscope $end
$upscope $end
$enddefinitions $end
$comment Show the parameter values. $end
$dumpall
b10100 /
b1 .
b10 -
b0 ,
b110010 +
$end
#0
$dumpvars
b0 0
b0 *
b0 )
0(
1'
0&
0%
0$
1#
b0 "
0!
$end
#5000
1&
#10000
0&
#15000
1&
#20000
b101 )
b101 *
0'
0&
#25000
1&
#30000
b11110 )
b11110 *
0&
#35000
1!
b1 "
b1 0
1&
#40000
b1000110 )
b1000110 *
0&
#45000
0#
1$
0!
b10 "
b10 0
1&
#50000
b101 )
b101 *
0&
#55000
1&
#60000
1#
0$
b0 "
b0 0
1'
0&
#65000
1&
#70000
0'
0&
#75000
1&
#80000
0&
#85000
1&
#90000
1(
0&
#95000
0#
1$
b10 "
b10 0
1%
1&
#100000
0(
0&
